cbm_files/__init__.py
cbm_files/basic_file.py
cbm_files/binary_file.py
cbm_files/data_file.py
cbm_files/expansion.py
cbm_files/pc64_file.py
cbm_files/program_file.py
cbm_files/tokenset_basic_v2.py
cbm_files/tokenset_basic_v3_5.py
cbm_files/tokenset_basic_v4.py
cbm_files/tokenset_basic_v7.py
cbm_files/tokenset_escape_40c128.py
cbm_files/tokenset_escape_80c128.py
cbm_files/tokenset_escape_c16.py
cbm_files/tokenset_escape_c64.py
cbm_files/tokenset_escape_pet.py
cbm_files/tokenset_escape_pet2001.py
cbm_files/tokenset_escape_vic20.py
cbm_files/tokenset_simons_basic.py
cbm_files/tokenset_vic20_super_expander.py
cbm_files/tokenset_vic20_super_expander_jp.py
cbm_files/tokenset_ycxb.py
cbm_files/tokensets.py
cbm_files/user_file.py
cbmfiles-2.3.dist-info/LICENSE
cbmfiles-2.3.dist-info/METADATA
cbmfiles-2.3.dist-info/WHEEL
cbmfiles-2.3.dist-info/top_level.txt
cbmfiles-2.3.dist-info/RECORD
